phantom/__init__.py
phantom/_base.py
phantom/_hypothesis.py
phantom/_version.py
phantom/boolean.py
phantom/bounds.py
phantom/datetime.py
phantom/errors.py
phantom/fn.py
phantom/interval.py
phantom/iso3166.py
phantom/negated.py
phantom/py.typed
phantom/re.py
phantom/schema.py
phantom/sized.py
phantom/_utils/__init__.py
phantom/_utils/misc.py
phantom/_utils/types.py
phantom/ext/__init__.py
phantom/ext/phonenumbers.py
phantom/predicates/__init__.py
phantom/predicates/_base.py
phantom/predicates/_utils.py
phantom/predicates/boolean.py
phantom/predicates/collection.py
phantom/predicates/datetime.py
phantom/predicates/generic.py
phantom/predicates/interval.py
phantom/predicates/numeric.py
phantom/predicates/re.py
phantom_types-3.0.2.dist-info/LICENSE
phantom_types-3.0.2.dist-info/METADATA
phantom_types-3.0.2.dist-info/WHEEL
phantom_types-3.0.2.dist-info/top_level.txt
phantom_types-3.0.2.dist-info/RECORD
