Metadata-Version: 2.1
Name: phantom-types
Version: 3.0.2
Summary: Phantom types for Python
Author-email: Anton Agestam <git@antonagestam.se>
License: BSD-3-Clause
Project-URL: Source Repository, https://github.com/antonagestam/phantom-types/
Project-URL: Documentation, https://phantom-types.readthedocs.io/en/stable/
Classifier: Intended Audience :: Developers
Classifier: Operating System :: OS Independent
Classifier: Programming Language :: Python
Classifier: Programming Language :: Python :: 3
Classifier: Programming Language :: Python :: 3 :: Only
Classifier: Programming Language :: Python :: 3.9
Classifier: Programming Language :: Python :: 3.10
Classifier: Programming Language :: Python :: 3.11
Classifier: Programming Language :: Python :: 3.12
Classifier: Programming Language :: Python :: 3.13
Classifier: Development Status :: 5 - Production/Stable
Requires-Python: >=3.9
License-File: LICENSE
Requires-Dist: typeguard!=4.3.*,>=4
Requires-Dist: typing-extensions>=4.3.0
Requires-Dist: numerary>=0.4.3
Provides-Extra: all
Requires-Dist: phantom-types[phonenumbers]; extra == "all"
Requires-Dist: phantom-types[pydantic]; extra == "all"
Requires-Dist: phantom-types[dateutil]; extra == "all"
Requires-Dist: phantom-types[hypothesis]; extra == "all"
Provides-Extra: dateutil
Requires-Dist: python-dateutil>=2.8.2; extra == "dateutil"
Provides-Extra: docs
Requires-Dist: phantom-types[all]; extra == "docs"
Requires-Dist: sphinx; extra == "docs"
Requires-Dist: sphinx-autodoc-typehints; extra == "docs"
Requires-Dist: furo; extra == "docs"
Provides-Extra: hypothesis
Requires-Dist: hypothesis[zoneinfo]>=6.68.0; extra == "hypothesis"
Provides-Extra: phonenumbers
Requires-Dist: phonenumbers>=8.12.41; extra == "phonenumbers"
Provides-Extra: pydantic
Requires-Dist: pydantic<2,>=1.9.0; extra == "pydantic"
Provides-Extra: test
Requires-Dist: mypy>=0.991; extra == "test"
Requires-Dist: pytest; extra == "test"
Requires-Dist: pytest-mypy-plugins>=1.9.3; extra == "test"
Requires-Dist: coverage; extra == "test"
Provides-Extra: type-check
Requires-Dist: phantom-types[all]; extra == "type-check"
Requires-Dist: mypy; extra == "type-check"
Requires-Dist: pytest; extra == "type-check"
Requires-Dist: types-python-dateutil; extra == "type-check"
